[
  {
    "type": "GENERIC",
    "id": "broken_tinyhammerdronesteel",
    "symbol": ",",
    "color": "yellow",
    "name": { "str": "broken tiny steel hammer drone", "str_pl": "broken tiny steel hammer drones" },
    "category": "other",
    "description": "The irreparably broken remains of a tiny-sized drone. Its weapon is irreparably damaged but the rest could be gutted for valuable parts.",
    "price": 30000,
    "price_postapoc": 1000,
    "material": [ "steel" ],
    "weight": "131500 g",
    "volume": "102500 ml",
    "melee_damage": { "bash": 6, "cut": 6 },
    "to_hit": -3,
    "flags": [ "TRADER_AVOID" ]
  },
  {
    "type": "GENERIC",
    "id": "broken_tinywreckingdronesteel",
    "symbol": ",",
    "color": "yellow",
    "name": { "str": "broken tiny steel wrecking drone", "str_pl": "broken tiny steel wrecking drones" },
    "category": "other",
    "description": "The irreparably broken remains of a tiny-sized drone. Its weapon is irreparably damaged but the rest could be gutted for valuable parts.",
    "price": 30000,
    "price_postapoc": 1000,
    "material": [ "steel" ],
    "weight": "131500 g",
    "volume": "102500 ml",
    "melee_damage": { "bash": 6, "cut": 6 },
    "to_hit": -3,
    "flags": [ "TRADER_AVOID" ]
  },
  {
    "type": "GENERIC",
    "id": "broken_tinysawdronesteel",
    "symbol": ",",
    "color": "yellow",
    "name": { "str": "broken tiny steel saw drone", "str_pl": "broken tiny steel saw drones" },
    "category": "other",
    "description": "The irreparably broken remains of a tiny-sized drone. Its weapon is irreparably damaged but the rest could be gutted for valuable parts.",
    "price": 30000,
    "price_postapoc": 1000,
    "material": [ "steel" ],
    "weight": "131500 g",
    "volume": "102500 ml",
    "melee_damage": { "bash": 6, "cut": 6 },
    "to_hit": -3,
    "flags": [ "TRADER_AVOID" ]
  },
  {
    "type": "GENERIC",
    "id": "broken_tinydrilldronesteel",
    "symbol": ",",
    "color": "yellow",
    "name": { "str": "broken tiny steel drill drone", "str_pl": "broken tiny steel drill drones" },
    "category": "other",
    "description": "The irreparably broken remains of a tiny-sized drone. Its weapon is irreparably damaged but the rest could be gutted for valuable parts.",
    "price": 30000,
    "price_postapoc": 1000,
    "material": [ "steel" ],
    "weight": "131500 g",
    "volume": "102500 ml",
    "melee_damage": { "bash": 6, "cut": 6 },
    "to_hit": -3,
    "flags": [ "TRADER_AVOID" ]
  },
  {
    "type": "GENERIC",
    "id": "broken_tinybladedronesteel",
    "symbol": ",",
    "color": "yellow",
    "name": { "str": "broken tiny steel blade drone", "str_pl": "broken tiny steel blade drones" },
    "category": "other",
    "description": "The irreparably broken remains of a tiny-sized drone. Its weapon is irreparably damaged but the rest could be gutted for valuable parts.",
    "price": 30000,
    "price_postapoc": 1000,
    "material": [ "steel" ],
    "weight": "131500 g",
    "volume": "102500 ml",
    "melee_damage": { "bash": 6, "cut": 6 },
    "to_hit": -3,
    "flags": [ "TRADER_AVOID" ]
  },
  {
    "type": "GENERIC",
    "id": "broken_tinyjawdronesteel",
    "symbol": ",",
    "color": "yellow",
    "name": { "str": "broken tiny steel jaw drone", "str_pl": "broken tiny steel jaw drones" },
    "category": "other",
    "description": "The irreparably broken remains of a tiny-sized drone. Its weapon is irreparably damaged but the rest could be gutted for valuable parts.",
    "price": 30000,
    "price_postapoc": 1000,
    "material": [ "steel" ],
    "weight": "131500 g",
    "volume": "102500 ml",
    "melee_damage": { "bash": 6, "cut": 6 },
    "to_hit": -3,
    "flags": [ "TRADER_AVOID" ]
  },
  {
    "type": "GENERIC",
    "id": "broken_tinybugdronesteel",
    "symbol": ",",
    "color": "yellow",
    "name": { "str": "broken tiny steel bug drone", "str_pl": "broken tiny steel bug drones" },
    "category": "other",
    "description": "The irreparably broken remains of a tiny-sized drone. Its weapon is irreparably damaged but the rest could be gutted for valuable parts.",
    "price": 30000,
    "price_postapoc": 1000,
    "material": [ "steel" ],
    "weight": "131500 g",
    "volume": "102500 ml",
    "melee_damage": { "bash": 6, "cut": 6 },
    "to_hit": -3,
    "flags": [ "TRADER_AVOID" ]
  },
  {
    "type": "GENERIC",
    "id": "broken_tinyflamedronesteel",
    "symbol": ",",
    "color": "yellow",
    "name": { "str": "broken tiny steel flame drone", "str_pl": "broken tiny steel flame drones" },
    "category": "other",
    "description": "The irreparably broken remains of a tiny-sized drone. Its weapon is irreparably damaged but the rest could be gutted for valuable parts.",
    "price": 30000,
    "price_postapoc": 1000,
    "material": [ "steel" ],
    "weight": "131500 g",
    "volume": "102500 ml",
    "melee_damage": { "bash": 6, "cut": 6 },
    "to_hit": -3,
    "flags": [ "TRADER_AVOID" ]
  },
  {
    "type": "GENERIC",
    "id": "broken_tinyflashdronesteel",
    "symbol": ",",
    "color": "yellow",
    "name": { "str": "broken tiny steel flash drone", "str_pl": "broken tiny steel flash drones" },
    "category": "other",
    "description": "The irreparably broken remains of a tiny-sized drone. Its weapon is irreparably damaged but the rest could be gutted for valuable parts.",
    "price": 30000,
    "price_postapoc": 1000,
    "material": [ "steel" ],
    "weight": "131500 g",
    "volume": "102500 ml",
    "melee_damage": { "bash": 6, "cut": 6 },
    "to_hit": -3,
    "flags": [ "TRADER_AVOID" ]
  }
]
