[
  {
    "type": "GENERIC",
    "id": "sawedbat",
    "name": { "str": "sawed-off bat" },
    "looks_like": "bat",
    "description": "A baseball bat with some length sawed off the thick end.",
    "weight": "800 g",
    "color": "brown",
    "symbol": "/",
    "material": [ "wood" ],
    "techniques": [ "WBLOCK_1", "BRUTAL", "PRECISE" ],
    "volume": "1250 ml",
    "longest_side": "60 cm",
    "bashing": 16,
    "to_hit": { "grip": "weapon", "length": "short", "surface": "any", "balance": "good" },
    "flags": [ "BELT_CLIP", "NONCONDUCTIVE", "DURABLE_MELEE" ],
    "weapon_category": [ "BATONS" ],
    "price": 16000,
    "price_postapoc": 1750
  },
  {
    "type": "GENERIC",
    "id": "sawedbat_nail",
    "name": { "str": "sawed-off nail bat" },
    "looks_like": "nailbat",
    "description": "A baseball bat with some length sawed off the thick end, nails have been hammered into the business end.",
    "weight": "826 g",
    "color": "brown",
    "symbol": "/",
    "material": [ "wood" ],
    "techniques": [ "WBLOCK_1", "BRUTAL", "PRECISE" ],
    "volume": "1250 ml",
    "longest_side": "60 cm",
    "bashing": 16,
    "cutting": 4,
    "to_hit": { "grip": "weapon", "length": "short", "surface": "any", "balance": "good" },
    "flags": [ "BELT_CLIP", "NONCONDUCTIVE", "DURABLE_MELEE", "STAB" ],
    "weapon_category": [ "BATONS" ],
    "price": 16000,
    "price_postapoc": 1750
  },
  {
    "type": "GENERIC",
    "id": "sawedbat_barbed",
    "name": { "str": "sawed-off barbed wire bat" },
    "looks_like": "bwirebat",
    "description": "A baseball bat with some length sawed off the thick end. Barbed wire has been wrapped around the end.",
    "weight": "938 g",
    "color": "brown",
    "symbol": "/",
    "material": [ "wood" ],
    "techniques": [ "WBLOCK_1", "BRUTAL", "PRECISE" ],
    "volume": "1250 ml",
    "longest_side": "60 cm",
    "bashing": 16,
    "cutting": 8,
    "to_hit": { "grip": "weapon", "length": "short", "surface": "any", "balance": "good" },
    "flags": [ "BELT_CLIP", "NONCONDUCTIVE", "DURABLE_MELEE" ],
    "weapon_category": [ "BATONS" ],
    "price": 16000,
    "price_postapoc": 1750
  },
  {
    "id": "elbow_skewer",
    "type": "ARMOR",
    "name": { "str_sp": "skewer elbow guard" },
    "description": "A pair of metal braces, each with a single sturdy spike attached.  When strapped to your hands, the spikes protrude 5 centimeters past your clenched fists.",
    "weight": "250 g",
    "volume": "300 ml",
    "price": 1100,
    "price_postapoc": 250,
    "bashing": 2,
    "cutting": 10,
    "to_hit": { "grip": "weapon", "length": "hand", "surface": "any", "balance": "good" },
    "material": [ "steel" ],
    "symbol": "[",
    "color": "light_gray",
    "warmth": 0,
    "material_thickness": 2,
    "flags": [ "WATER_FRIENDLY", "DURABLE_MELEE", "STAB", "OUTER" ],
    "armor": [
      {
        "covers": [ "arm_l", "arm_r" ],
        "encumbrance": 5,
        "coverage": 20,
        "specifically_covers": [ "arm_elbow_r", "arm_elbow_l" ]
      }
    ]
  },
  {
    "id": "knee_skewer",
    "type": "ARMOR",
    "name": { "str_sp": "skewer knee guard" },
    "description": "A pair of metal braces, each with a single sturdy spike attached.  When strapped to your hands, the spikes protrude 5 centimeters past your clenched fists.",
    "weight": "250 g",
    "volume": "300 ml",
    "price": 1100,
    "price_postapoc": 250,
    "bashing": 2,
    "cutting": 10,
    "to_hit": { "grip": "weapon", "length": "hand", "surface": "any", "balance": "good" },
    "material": [ "steel" ],
    "symbol": "[",
    "color": "light_gray",
    "warmth": 0,
    "material_thickness": 2,
    "flags": [ "WATER_FRIENDLY", "DURABLE_MELEE", "STAB", "OUTER" ],
    "armor": [
      {
        "covers": [ "leg_l", "leg_r" ],
        "encumbrance": 5,
        "coverage": 20,
        "specifically_covers": [ "leg_knee_l", "leg_knee_r" ]
      }
    ]
  },
  {
    "id": "foot_skewer",
    "type": "ARMOR",
    "name": { "str_sp": "skewer sabatons" },
    "description": "A pair of metal braces, each with a single sturdy spike attached.  When strapped to your hands, the spikes protrude 5 centimeters past your clenched fists.",
    "weight": "250 g",
    "volume": "300 ml",
    "price": 1100,
    "price_postapoc": 250,
    "bashing": 2,
    "cutting": 10,
    "to_hit": { "grip": "weapon", "length": "hand", "surface": "any", "balance": "good" },
    "material": [ "steel" ],
    "symbol": "[",
    "color": "light_gray",
    "warmth": 0,
    "material_thickness": 2,
    "flags": [ "WATER_FRIENDLY", "DURABLE_MELEE", "STAB", "OUTER" ],
    "armor": [ { "encumbrance": 5, "coverage": 20, "covers": [ "foot_l", "foot_r" ] } ]
  },
  {
    "id": "feder",
    "type": "TOOL",
    "symbol": "/",
    "color": "light_gray",
    "name": { "str": "feder" },
    "looks_like": "longsword",
    "description": "A training sword made of metal, usually with a folded or curled tip.",
    "price": 13000,
    "price_postapoc": 6000,
    "material": [ "steel" ],
    "flags": [ "DURABLE_MELEE", "SHEATH_SWORD" ],
    "weapon_category": [ "MEDIEVAL_SWORDS", "LONG_SWORDS", "GREAT_SWORDS" ],
    "techniques": [ "WBLOCK_2", "BRUTAL", "RAPID" ],
    "weight": "1414 g",
    "volume": "2750 ml",
    "longest_side": "120 cm",
    "bashing": 22,
    "to_hit": { "grip": "weapon", "length": "long", "surface": "line", "balance": "good" },
    "category": "weapons"
  },
    {
    "id": "knife_rondel",
    "type": "TOOL",
    "name": { "str": "rondel" },
    "category": "weapons",
    "description": "A reproduction of a medieval dagger forged from stainless steel.  It is not the sharpest tool in the shed, but it is certainly one of the largest.",
    "weight": "440 g",
    "volume": "250 ml",
    "longest_side": "44 cm",
    "techniques": [ "WBLOCK_2", "RAPID" ],
    "price": 19590,
    "bashing": 4,
    "cutting": 27,
    "looks_like": "baselard",
    "to_hit": { "grip": "weapon", "length": "short", "surface": "line", "balance": "good" },
    "material": [ "steel" ],
    "symbol": ";",
    "color": "dark_gray",
    "qualities": [ [ "CUT", 2 ], [ "BUTCHER", 15 ] ],
    "flags": [ "SHEATH_KNIFE", "STAB" ],
    "weapon_category": [ "MEDIUM_SWORDS" ]
  },
  {
    "id": "knife_stiletto",
    "type": "TOOL",
    "name": { "str": "stiletto dagger" },
    "category": "weapons",
    "description": "A reproduction of a medieval dagger forged from stainless steel.  It is not the largest tool in the shed, but it is certainly one of the sharpest.",
    "weight": "200 g",
    "volume": "250 ml",
    "longest_side": "50 cm",
    "techniques": [ "RAPID", "PRECISE" ],
    "looks_like": "switchblade",
    "price": 19590,
    "bashing": 1,
    "cutting": 23,
    "to_hit": { "grip": "weapon", "length": "short", "surface": "line", "balance": "good" },
    "material": [ "steel" ],
    "symbol": ";",
    "color": "dark_gray",
    "qualities": [ [ "CUT", 2 ], [ "BUTCHER", 15 ] ],
    "flags": [ "SHEATH_KNIFE", "STAB" ],
    "weapon_category": [ "KNIVES" ]
  },
  {
    "id": "redsteel_morningstar",
    "type": "TOOL",
    "symbol": "/",
    "color": "light_gray",
    "name": { "str": "redsteel morningstar" },
    "description": "A brutal morningstar made of red metal with a mana pearl stuck in it's hilt. The blade is made of redsteel, a substance that's nearly impossible to find or create. It adores the taste of blood above all else, draining it from anyone it touches.",
    "price": 80000,
    "looks_like": "morningstar",
    "material": [ "glassteel" ],
    "flags": [ "DURABLE_MELEE", "SHEATH_KNIFE", "MAGIC_FOCUS", "STAB" ],
    "weapon_category": [ "MACES" ],
    "techniques": [ "WBLOCK_1", "SWEEP" ],
    "weight": "1600 g",
    "volume": "1500 ml",
    "longest_side": "100 cm",
    "bashing": 33,
    "cutting": 10,
    "to_hit": { "grip": "weapon", "length": "short", "surface": "any", "balance": "good" },
    "category": "weapons",
    "relic_data": {
      "passive_effects": [
        {
          "has": "WIELD",
          "condition": "ALWAYS",
          "values": [ { "value": "DEXTERITY", "add": 2 } ],
          "hit_you_effect": [ { "id": "bleed" } ]
        }
      ]
    },
    "qualities": [ [ "HAMMER", 1 ] ]
  },
  {
    "id": "greensteel_spear",
    "type": "TOOL",
    "symbol": "/",
    "color": "light_gray",
    "name": { "str": "greensteel spear" },
    "description": "A long, menacing spear made of green metal with a mana pearl stuck in it's hilt. The blade and shaft are made of greensteel, a substance that's nearly impossible to find or create. It adores lifeforce above all else, draining it from anyone it touches.",
    "price": 80000,
    "looks_like": "spear_steel",
    "material": [ "glassteel" ],
    "flags": [ "DURABLE_MELEE", "SHEATH_SPEAR", "MAGIC_FOCUS", "SPEAR", "REACH_ATTACK" ],
    "weapon_category": [ "SPEARS", "POLEARMS" ],
    "techniques": [ "WBLOCK_1", "IMPALE" ],
    "weight": "1050 g",
    "volume": "1250 ml",
    "longest_side": "180 cm",
    "bashing": 5,
    "cutting": 35,
    "to_hit": { "grip": "weapon", "length": "long", "surface": "point", "balance": "good" },
    "category": "weapons",
    "relic_data": {
      "passive_effects": [
        {
          "has": "WIELD",
          "condition": "ALWAYS",
          "values": [ { "value": "PERCEPTION", "add": 2 } ],
          "hit_you_effect": [ { "id": "devour" } ]
        }
      ]
    },
    "qualities": [ [ "COOK", 1 ], [ "BUTCHER", -10 ] ]
  },
  {
    "type": "recipe",
    "activity_level": "LIGHT_EXERCISE",
    "result": "sawedbat",
    "category": "CC_WEAPON",
    "subcategory": "CSC_WEAPON_BASHING",
    "skill_used": "fabrication",
    "time": "10 m",
    "autolearn": true,
    "qualities": [ { "id": "SAW_W", "level": 1 } ],
    "proficiencies": [ { "proficiency": "prof_carpentry_basic", "fail_multiplier": 1 } ],
    "components": [ [ [ "bat", 1 ] ] ]
  },
  {
    "type": "recipe",
    "activity_level": "LIGHT_EXERCISE",
    "result": "sawedbat_nail",
    "category": "CC_WEAPON",
    "subcategory": "CSC_WEAPON_BASHING",
    "skill_used": "fabrication",
    "time": "10 m",
    "autolearn": true,
    "qualities": [ { "id": "HAMMER", "level": 1 } ],
    "proficiencies": [ { "proficiency": "prof_carpentry_basic", "fail_multiplier": 1 } ],
    "components": [ [ [ "sawedbat", 1 ] ], [ [ "nail", 6 ] ] ]
  },
  {
    "type": "recipe",
    "activity_level": "LIGHT_EXERCISE",
    "result": "sawedbat_barbed",
    "category": "CC_WEAPON",
    "subcategory": "CSC_WEAPON_BASHING",
    "skill_used": "fabrication",
    "time": "10 m",
    "autolearn": true,
    "components": [ [ [ "sawedbat", 1 ] ], [ [ "wire_barbed", 1 ] ] ]
  },
  {
    "type": "recipe",
    "activity_level": "BRISK_EXERCISE",
    "result": "knife_rondel",
    "category": "CC_WEAPON",
    "subcategory": "CSC_WEAPON_CUTTING",
    "skill_used": "fabrication",
    "difficulty": 4,
    "time": "5 h",
    "autolearn": true,
    "using": [ [ "blacksmithing_standard", 4 ], [ "steel_standard", 1 ] ],
    "proficiencies": [
      { "proficiency": "prof_metalworking" },
      { "proficiency": "prof_blacksmithing" },
      { "proficiency": "prof_bladesmith" },
      { "proficiency": "prof_leatherworking_basic", "fail_multiplier": 1 }
    ],
    "qualities": [ { "id": "GRIND", "level": 2 } ],
    "tools": [ [ [ "hotcut", -1 ] ] ],
    "components": [ [ [ "fur", 1 ], [ "leather", 1 ] ] ]
  },
  {
    "type": "recipe",
    "activity_level": "BRISK_EXERCISE",
    "result": "knife_stiletto",
    "category": "CC_WEAPON",
    "subcategory": "CSC_WEAPON_CUTTING",
    "skill_used": "fabrication",
    "difficulty": 4,
    "time": "5 h",
    "autolearn": true,
    "using": [ [ "blacksmithing_standard", 4 ], [ "steel_standard", 1 ] ],
    "proficiencies": [
      { "proficiency": "prof_metalworking" },
      { "proficiency": "prof_blacksmithing" },
      { "proficiency": "prof_bladesmith" },
      { "proficiency": "prof_leatherworking_basic", "fail_multiplier": 1 }
    ],
    "qualities": [ { "id": "GRIND", "level": 2 } ],
    "tools": [ [ [ "hotcut", -1 ] ] ],
    "components": [ [ [ "fur", 1 ], [ "leather", 1 ] ] ]
  },
  {
    "type": "recipe",
    "activity_level": "LIGHT_EXERCISE",
    "result": "elbow_skewer",
    "category": "CC_WEAPON",
    "subcategory": "CSC_WEAPON_BASHING",
    "skill_used": "fabrication",
    "time": "10 m",
    "autolearn": true,
    "components": [ [ [ "knuckle_skewer", 1 ] ] ]
  },
  {
    "type": "recipe",
    "activity_level": "LIGHT_EXERCISE",
    "result": "knee_skewer",
    "category": "CC_WEAPON",
    "subcategory": "CSC_WEAPON_BASHING",
    "skill_used": "fabrication",
    "time": "10 m",
    "autolearn": true,
    "components": [ [ [ "knuckle_skewer", 1 ] ] ]
  },
  {
    "type": "recipe",
    "activity_level": "LIGHT_EXERCISE",
    "result": "foot_skewer",
    "category": "CC_WEAPON",
    "subcategory": "CSC_WEAPON_BASHING",
    "skill_used": "fabrication",
    "time": "10 m",
    "autolearn": true,
    "components": [ [ [ "knuckle_skewer", 1 ] ] ]
  }
]
